demo.py
python_policy_demo-1.3.0.dist-info/LICENSE
python_policy_demo-1.3.0.dist-info/METADATA
python_policy_demo-1.3.0.dist-info/WHEEL
python_policy_demo-1.3.0.dist-info/top_level.txt
python_policy_demo-1.3.0.dist-info/RECORD
